permutations_younes/__init__.py
permutations_younes/permutations.py
permutations_younes-0.0.1.dist-info/licenses/LICENSE
permutations_younes-0.0.1.dist-info/METADATA
permutations_younes-0.0.1.dist-info/WHEEL
permutations_younes-0.0.1.dist-info/top_level.txt
permutations_younes-0.0.1.dist-info/RECORD
