Metadata-Version: 2.4
Name: permutations-younes
Version: 0.0.1
Summary: A Python utility to generate all permutations of a list of elements using Heap's algorithm.
Author-email: Younes <younessfire10@gmail.com>
License-Expression: MIT
Project-URL: Homepage, https://github.com/procrastinator-101/permutations
Project-URL: Issues, https://github.com/procrastinator-101/permutations/issues
Classifier: Programming Language :: Python :: 3
Classifier: Operating System :: OS Independent
Requires-Python: >=3.10
License-File: LICENSE
Dynamic: license-file
